Botte/__init__.py
Botte/apihelper.py
Botte/async_telebot.py
Botte/asyncio_filters.py
Botte/asyncio_handler_backends.py
Botte/asyncio_helper.py
Botte/callback_data.py
Botte/custom_filters.py
Botte/falcon.py
Botte/formatting.py
Botte/gpt3.py
Botte/handler_backends.py
Botte/imggen.py
Botte/pollinations.py
Botte/service_utils.py
Botte/types.py
Botte/util.py
Botte/version.py
Botte/asyncio_storage/__init__.py
Botte/asyncio_storage/base_storage.py
Botte/asyncio_storage/memory_storage.py
Botte/asyncio_storage/pickle_storage.py
Botte/asyncio_storage/redis_storage.py
Botte/ext/__init__.py
Botte/ext/reloader.py
Botte/ext/aio/__init__.py
Botte/ext/aio/webhooks.py
Botte/ext/sync/__init__.py
Botte/ext/sync/webhooks.py
Botte/storage/__init__.py
Botte/storage/base_storage.py
Botte/storage/memory_storage.py
Botte/storage/pickle_storage.py
Botte/storage/redis_storage.py
tests/__init__.py
tests/ok.py
tests/test_handler_backends.py
tests/test_telebot.py
tests/test_types.py
Botte-0.6.2.dist-info/LICENSE
Botte-0.6.2.dist-info/METADATA
Botte-0.6.2.dist-info/WHEEL
Botte-0.6.2.dist-info/top_level.txt
Botte-0.6.2.dist-info/RECORD
