Metadata-Version: 2.1
Name: Botte
Version: 0.6.2
Summary: The most easiest telegram package that helps you to code your bot faster
Home-page: https://github.com/Teameviral/botte
Author: Avishek Bhattacharjee
Author-email: wbavishek@gmail.com
Classifier: License :: OSI Approved :: MIT License
Classifier: Programming Language :: Python :: 3
Classifier: Programming Language :: Python :: 3.7
Classifier: Programming Language :: Python :: 3.8
Classifier: Programming Language :: Python :: 3.9
Classifier: Operating System :: OS Independent
Requires-Python: >=3.6
License-File: LICENSE
Requires-Dist: requests
Requires-Dist: aiohttp
Requires-Dist: openai
